[
    {
        "id": "07pdrae4",
        "error": "Expecting value: line 1 column 1 (char 0)",
        "data": "Empty DataFrame\nColumns: []\nIndex: []"
    },
    {
        "id": "so9g6z6y",
        "error": "Expecting value: line 1 column 1 (char 0)",
        "data": "Empty DataFrame\nColumns: []\nIndex: []"
    },
    {
        "id": "92hiw2o1",
        "error": "Expecting value: line 1 column 1 (char 0)",
        "data": "Empty DataFrame\nColumns: []\nIndex: []"
    },
    {
        "id": "zopf014s",
        "error": "Expecting value: line 1 column 1 (char 0)",
        "data": "Empty DataFrame\nColumns: []\nIndex: []"
    },
    {
        "id": "ly3lz8u8",
        "error": "Expecting value: line 1 column 1 (char 0)",
        "data": "Empty DataFrame\nColumns: []\nIndex: []"
    },
    {
        "id": "dejab9n7",
        "error": "Expecting value: line 1 column 1 (char 0)",
        "data": "Empty DataFrame\nColumns: []\nIndex: []"
    },
    {
        "id": "qppe0ic1",
        "error": "Expecting value: line 1 column 1 (char 0)",
        "data": "Empty DataFrame\nColumns: []\nIndex: []"
    },
    {
        "id": "bymmhzf0",
        "error": "Expecting value: line 1 column 1 (char 0)",
        "data": "Empty DataFrame\nColumns: []\nIndex: []"
    },
    {
        "id": "z62om6a5",
        "error": "Expecting value: line 1 column 1 (char 0)",
        "data": "Empty DataFrame\nColumns: []\nIndex: []"
    },
    {
        "id": "ylg71ahd",
        "error": "Expecting value: line 1 column 1 (char 0)",
        "data": "Empty DataFrame\nColumns: []\nIndex: []"
    },
    {
        "id": "brg58jrj",
        "error": "Invalid control character at: line 1 column 3189 (char 3188)",
        "data": "Empty DataFrame Columns: [] Index: []"
    }
]